wiimake/__init__.py
wiimake/__main__.py
wiimake/assembly_code.py
wiimake/config_parser.py
wiimake/iso.py
wiimake/linker_scripts.py
wiimake/pipeline.py
wiimake/wiimake.py
wiimake/wiimake_isotool.py
wiimake-1.99.0.dist-info/DESCRIPTION.rst
wiimake-1.99.0.dist-info/METADATA
wiimake-1.99.0.dist-info/RECORD
wiimake-1.99.0.dist-info/WHEEL
wiimake-1.99.0.dist-info/entry_points.txt
wiimake-1.99.0.dist-info/metadata.json
wiimake-1.99.0.dist-info/top_level.txt
