Metadata-Version: 2.0
Name: wiimake
Version: 1.99.0
Summary: Command line tool for building Gamecube/Wii mods
Home-page: UNKNOWN
Author: Tom Sherman
Author-email: tomsherman159@gmail.com
License: UNKNOWN
Platform: UNKNOWN
